{"public":{"folders":[{"name":"演示1","children":[{"name":"演示2","files":[]}],"passwordHash":"","passwordSalt":""},{"name":"A ","children":[],"passwordHash":"","passwordSalt":""}],"trash":[]},"private":{"88899907":{"folders":[{"name":"我的文件","children":[{"name":"文档","files":[]},{"name":"图片","files":[]},{"name":"其他","files":[]}],"passwordHash":"","passwordSalt":""},{"name":"A ","children":[{"name":"a","files":[{"name":"智汇社活动申请表.docx","type":"file","size":12747,"mime":"application/vnd.openxmlformats-officedocument.wordprocessingml.document"},{"name":"剧本.txt","type":"file","size":4128,"mime":"text/plain"},{"name":"疑难杂症总结.docx","type":"file","size":39212,"mime":"application/vnd.openxmlformats-officedocument.wordprocessingml.document"}]},{"name":"b","files":[]}],"passwordHash":"","passwordSalt":""}],"trash":[]},"yangui1":{"folders":[{"name":"演示3","children":[{"name":"演示4","files":[{"name":"前端源代码.txt","type":"file","size":77922,"mime":"text/plain"},{"name":"正在优化的后端方案.txt","size":49364,"mime":"text/plain","uploadTime":1781527090831},{"name":"正在优化的前端方案.txt","size":77465,"mime":"text/plain","uploadTime":1781527226684}]}],"passwordHash":"","passwordSalt":""}],"trash":[],"version":2},"yangui2":{"folders":[{"name":"我的文件","passwordHash":"","passwordSalt":"","children":[{"name":"文档","files":[{"name":"正在优化的前端方案.txt","size":77465,"mime":"text/plain","uploadTime":1781530035857}]},{"name":"图片","files":[]},{"name":"其他","files":[]}]}],"trash":[],"version":1},"yangui":{"version":2,"folders":[],"trash":[{"type":"folder","folder":{"id":"66c47a27-0fd6-4ec8-b911-bd3de9e70be3","name":"错误文件夹","passwordHash":"","passwordSalt":"","children":[]},"deletedAt":1781531336728}]},"yangui888":{"version":7,"folders":[{"id":"f34b83a7-b75d-44cf-892e-8a2f2290220f","name":"发展方向","hasPassword":false,"children":[{"id":"257a1b58-a416-4302-bcfd-6e0b43f9d4de","name":"6.16","files":[{"name":"后续方向.txt","size":3113,"mime":"text/plain","uploadTime":1781543046744}]}],"passwordHash":"","passwordSalt":""},{"id":"9ec526fc-1ecb-45ed-b8a2-81592fbfd6ae","name":"账号接码","passwordHash":"","passwordSalt":"","children":[{"id":"2ab619e4-20d7-456e-b7c8-fc900f0d3b09","name":"总文件","files":[{"name":"工作号接码.zip","size":58243,"mime":"application/x-zip-compressed","uploadTime":1781543407967}]}]}],"trash":[{"type":"folder","folder":{"id":"6f72329a-bfd6-435e-b824-1c5efb396dfe","name":"我的文件","hasPassword":false,"children":[{"id":"bbb46623-6acd-41e5-b5d3-1f0cf623da27","name":"文档","files":[]},{"id":"89866246-bfec-42a3-9a68-db844c47f41a","name":"图片","files":[]},{"id":"af1eae6c-df7b-41dc-a4d4-61bf44826bc6","name":"其他","files":[]}]},"deletedAt":1781543015243}]}}}